rpq/__init__.py
rpq/nn.py
rpq/utils.py
rpq/models/__init__.py
rpq/models/rpqopt.py
rpq/models/rpqopt_sc.py
rpq/models/rpqvit.py
rpq/models/rpqvit_sc.py
RPQ_pytorch-0.0.34.dist-info/LICENSE
RPQ_pytorch-0.0.34.dist-info/METADATA
RPQ_pytorch-0.0.34.dist-info/WHEEL
RPQ_pytorch-0.0.34.dist-info/top_level.txt
RPQ_pytorch-0.0.34.dist-info/RECORD
