Metadata-Version: 2.1
Name: RPQ-pytorch
Version: 0.0.34
Summary: Reverse Product Quantization (RPQ) of weights to reduce static memory usage.
Home-page: https://github.com/a-kore/RPQ-pytorch
Author: Ali Kore
Author-email: akore654@gmail.com
License: MIT
Keywords: artificial intelligence,AI,machine learning,deep learning,pytorch,quantization,product quantization,reverse product quantization,memory reduction
Classifier: Development Status :: 4 - Beta
Classifier: Intended Audience :: Developers
Classifier: Topic :: Scientific/Engineering :: Artificial Intelligence
Classifier: License :: OSI Approved :: MIT License
Classifier: Programming Language :: Python :: 3.10
License-File: LICENSE
Requires-Dist: torch >=1.6
Requires-Dist: einops >=0.6
Requires-Dist: transformers >=4.0
Requires-Dist: vit-pytorch >=0.40
